__init__.py
topsis.py
topsis_abhirajsinghjhajj-0.1.0.dist-info/licenses/LICENSE.txt
topsis_abhirajsinghjhajj-0.1.0.dist-info/METADATA
topsis_abhirajsinghjhajj-0.1.0.dist-info/WHEEL
topsis_abhirajsinghjhajj-0.1.0.dist-info/top_level.txt
topsis_abhirajsinghjhajj-0.1.0.dist-info/RECORD
