Metadata-Version: 2.4
Name: Topsis_AbhirajSinghJhajj
Version: 0.1.0
Summary: A Python package for TOPSIS method
Author-email: Abhiraj Singh Jhajj <your-email@example.com>
Requires-Python: >=3.7
License-File: LICENSE.txt
Requires-Dist: numpy
Requires-Dist: pandas
Dynamic: license-file
